 {
  "English": [
    {
      "type": "category",
      "label": "Release Notes",
      "items": [
        {
          "type": "category",
          "label": "StarRocks",
          "items": [ "release-3.1", "release-3.0", "release-2.5", "release-2.4", "release-2.3", "release-2.2", "release-2.1", "release-2.0", "release-1.19" ]
        },
        {
          "type": "category",
          "label": "StarRocks Ecosystem",
          "items": ["kafka_connector", "flink_connector", "spark_connector", "starrocks-kubernetes-operator" ]
        }
      ]
    }
   ],
  "Chinese": [
    {
      "type": "category",
      "label": "Release Notes",
      "items": [
        {
          "type": "category",
          "label": "StarRocks",
          "items": [ "release-3.1", "release-3.0", "release-2.5", "release-2.4", "release-2.3", "release-2.2", "release-2.1", "release-2.0", "release-1.19" ]
        },
        {
          "type": "category",
          "label": "StarRocks Ecosystem",
          "items": ["kafka_connector", "flink_connector", "spark_connector", "starrocks-kubernetes-operator" ]
        }
      ]
    }
   ]
 }
